speedscope_to_codeperf/__init__.py
speedscope_to_codeperf/cli.py
speedscope_to_codeperf/git.py
speedscope_to_codeperf/schema/speedscope.py
speedscope_to_codeperf-0.1.0.dist-info/entry_points.txt
speedscope_to_codeperf-0.1.0.dist-info/LICENSE
speedscope_to_codeperf-0.1.0.dist-info/WHEEL
speedscope_to_codeperf-0.1.0.dist-info/METADATA
speedscope_to_codeperf-0.1.0.dist-info/RECORD
