Metadata-Version: 2.1
Name: speedscope-to-codeperf
Version: 0.1.0
Summary: 
Author: filipecosta90
Author-email: filipecosta.90@gmail.com
Requires-Python: >=3.8,<4.0
Classifier: Programming Language :: Python :: 3
Classifier: Programming Language :: Python :: 3.10
Classifier: Programming Language :: Python :: 3.8
Classifier: Programming Language :: Python :: 3.9
Requires-Dist: GitPython (>=3.1.27,<4.0.0)
Requires-Dist: jsonschema (>=4.4.0,<5.0.0)
Requires-Dist: pandas (>=1.4.2,<2.0.0)
Requires-Dist: requests (>=2.27.1,<3.0.0)
Requires-Dist: toml (>=0.10.2,<0.11.0)
